homelette/__init__.py
homelette/alignment.py
homelette/evaluation.py
homelette/organization.py
homelette/pdb_io.py
homelette/routines.py
homelette/extension/__init__.py
homelette/extension/extension_foldx.py
homelette-1.4.dist-info/LICENSE
homelette-1.4.dist-info/METADATA
homelette-1.4.dist-info/WHEEL
homelette-1.4.dist-info/top_level.txt
homelette-1.4.dist-info/RECORD
