Metadata-Version: 2.1
Name: homelette
Version: 1.4
Summary: A unified and modular interface to homology modelling software
Home-page: https://github.com/philippjunk/homelette/
Author: Philipp Junk, Christina Kiel
Author-email: philipp.junk@ucdconnect.ie
License: MIT
Keywords: homology modelling,bioinformatics
Platform: UNKNOWN
Classifier: Operating System :: OS Independent
Classifier: License :: OSI Approved :: MIT License
Classifier: Programming Language :: Python
Classifier: Programming Language :: Python :: 3
Classifier: Programming Language :: Python :: 3.6
Classifier: Programming Language :: Python :: 3.7
Classifier: Programming Language :: Python :: 3.8
Classifier: Programming Language :: Python :: 3.9
Classifier: Intended Audience :: Science/Research
Classifier: Topic :: Scientific/Engineering :: Bio-Informatics
Requires-Python: >=3.6
Requires-Dist: pandas
